{"dependencies":[{"name":"/Users/terminallychill/Sites/zentone/package.json","includedInParent":true,"mtime":1524563952088},{"name":"/Users/terminallychill/Sites/zentone/node_modules/passport-google-oauth/package.json","includedInParent":true,"mtime":1454557063000},{"name":"passport-google-oauth1","loc":{"line":2,"column":28}},{"name":"passport-google-oauth20","loc":{"line":3,"column":29}}],"generated":{"js":"// Load modules.\nvar OAuthStrategy = require('passport-google-oauth1');\nvar OAuth2Strategy = require('passport-google-oauth20');\n\n// Exports.\nexports.Strategy = exports.OAuthStrategy = OAuthStrategy;\nexports.OAuth2Strategy = OAuth2Strategy;","map":{"mappings":[{"generated":{"line":1,"column":0},"source":"node_modules/passport-google-oauth/lib/index.js","original":{"line":1,"column":0}},{"generated":{"line":2,"column":0},"source":"node_modules/passport-google-oauth/lib/index.js","original":{"line":2,"column":0}},{"name":"OAuthStrategy","generated":{"line":2,"column":4},"source":"node_modules/passport-google-oauth/lib/index.js","original":{"line":2,"column":4}},{"name":"require","generated":{"line":2,"column":20},"source":"node_modules/passport-google-oauth/lib/index.js","original":{"line":2,"column":20}},{"generated":{"line":2,"column":28},"source":"node_modules/passport-google-oauth/lib/index.js","original":{"line":2,"column":28}},{"generated":{"line":2,"column":52},"source":"node_modules/passport-google-oauth/lib/index.js","original":{"line":2,"column":20}},{"generated":{"line":2,"column":53},"source":"node_modules/passport-google-oauth/lib/index.js","original":{"line":2,"column":0}},{"generated":{"line":3,"column":0},"source":"node_modules/passport-google-oauth/lib/index.js","original":{"line":3,"column":0}},{"name":"OAuth2Strategy","generated":{"line":3,"column":4},"source":"node_modules/passport-google-oauth/lib/index.js","original":{"line":3,"column":4}},{"name":"require","generated":{"line":3,"column":21},"source":"node_modules/passport-google-oauth/lib/index.js","original":{"line":3,"column":21}},{"generated":{"line":3,"column":29},"source":"node_modules/passport-google-oauth/lib/index.js","original":{"line":3,"column":29}},{"generated":{"line":3,"column":54},"source":"node_modules/passport-google-oauth/lib/index.js","original":{"line":3,"column":21}},{"generated":{"line":3,"column":55},"source":"node_modules/passport-google-oauth/lib/index.js","original":{"line":3,"column":0}},{"generated":{"line":5,"column":0},"source":"node_modules/passport-google-oauth/lib/index.js","original":{"line":5,"column":0}},{"name":"exports","generated":{"line":6,"column":0},"source":"node_modules/passport-google-oauth/lib/index.js","original":{"line":6,"column":0}},{"name":"Strategy","generated":{"line":6,"column":8},"source":"node_modules/passport-google-oauth/lib/index.js","original":{"line":6,"column":8}},{"generated":{"line":6,"column":16},"source":"node_modules/passport-google-oauth/lib/index.js","original":{"line":6,"column":0}},{"name":"exports","generated":{"line":6,"column":19},"source":"node_modules/passport-google-oauth/lib/index.js","original":{"line":7,"column":0}},{"name":"OAuthStrategy","generated":{"line":6,"column":27},"source":"node_modules/passport-google-oauth/lib/index.js","original":{"line":7,"column":8}},{"generated":{"line":6,"column":40},"source":"node_modules/passport-google-oauth/lib/index.js","original":{"line":7,"column":0}},{"name":"OAuthStrategy","generated":{"line":6,"column":43},"source":"node_modules/passport-google-oauth/lib/index.js","original":{"line":7,"column":24}},{"generated":{"line":6,"column":56},"source":"node_modules/passport-google-oauth/lib/index.js","original":{"line":6,"column":0}},{"name":"exports","generated":{"line":7,"column":0},"source":"node_modules/passport-google-oauth/lib/index.js","original":{"line":8,"column":0}},{"name":"OAuth2Strategy","generated":{"line":7,"column":8},"source":"node_modules/passport-google-oauth/lib/index.js","original":{"line":8,"column":8}},{"generated":{"line":7,"column":22},"source":"node_modules/passport-google-oauth/lib/index.js","original":{"line":8,"column":0}},{"name":"OAuth2Strategy","generated":{"line":7,"column":25},"source":"node_modules/passport-google-oauth/lib/index.js","original":{"line":8,"column":25}},{"generated":{"line":7,"column":39},"source":"node_modules/passport-google-oauth/lib/index.js","original":{"line":8,"column":0}}],"sources":{"node_modules/passport-google-oauth/lib/index.js":"// Load modules.\nvar OAuthStrategy = require('passport-google-oauth1');\nvar OAuth2Strategy = require('passport-google-oauth20')\n\n// Exports.\nexports.Strategy =\nexports.OAuthStrategy = OAuthStrategy;\nexports.OAuth2Strategy = OAuth2Strategy;\n"},"lineCount":null}},"hash":"77af6904c4f9a546aecb3a7c8c06b907","cacheData":{"env":{}}}